simplekg/KnowledgeGraphGenerator_FullDocumentation.html
simplekg/__init__.py
simplekg/cli.py
simplekg/documentation.txt
simplekg/kg.py
simplekg/kg_back.py
simplekg/models.py
simplekg/nltk_setup.py
simplekg/ontologies.txt
simplekg/tests.py
simplekg/utils.py
simplekg-0.1.2.dist-info/licenses/LICENSE
simplekg-0.1.2.dist-info/METADATA
simplekg-0.1.2.dist-info/WHEEL
simplekg-0.1.2.dist-info/entry_points.txt
simplekg-0.1.2.dist-info/top_level.txt
simplekg-0.1.2.dist-info/RECORD
