Metadata-Version: 2.4
Name: simplekg
Version: 0.1.2
Summary: A complete workflow for generating, normalizing, and visualizing Knowledge Graphs from unstructured Hebrew text
Home-page: https://gitlab.com/millerhadar/simplekg
Author: Hadar Miller
Author-email: Hadar Miller <miller.hadar@gmail.com>
License-Expression: MIT
Project-URL: Homepage, https://gitlab.com/millerhadar/simplekg
Project-URL: Bug Tracker, https://gitlab.com/millerhadar/simplekg/-/issues
Project-URL: Documentation, https://gitlab.com/millerhadar/simplekg/-/blob/main/README.md
Project-URL: Source Code, https://gitlab.com/millerhadar/simplekg
Keywords: knowledge-graph,nlp,hebrew,ontology,skos,rdf,extraction
Classifier: Development Status :: 3 - Alpha
Classifier: Intended Audience :: Developers
Classifier: Intended Audience :: Science/Research
Classifier: Topic :: Scientific/Engineering :: Artificial Intelligence
Classifier: Topic :: Text Processing :: Linguistic
Classifier: Programming Language :: Python :: 3
Classifier: Programming Language :: Python :: 3.8
Classifier: Programming Language :: Python :: 3.9
Classifier: Programming Language :: Python :: 3.10
Classifier: Programming Language :: Python :: 3.11
Classifier: Operating System :: OS Independent
Requires-Python: >=3.8
License-File: LICENSE
Requires-Dist: dspy-ai>=2.6.24
Requires-Dist: openai>=1.61.0
Requires-Dist: numpy<2
Requires-Dist: pydantic>=2.0.0
Requires-Dist: torch>=1.11.0
Requires-Dist: sentence-transformers>=2.0.0
Requires-Dist: scikit-learn
Requires-Dist: python-dotenv
Requires-Dist: pyvis>=0.3.2
Requires-Dist: nltk>=3.8
Provides-Extra: dev
Requires-Dist: ipywidgets; extra == "dev"
Requires-Dist: jupyter; extra == "dev"
Requires-Dist: pytest; extra == "dev"
Requires-Dist: pytest-cov; extra == "dev"
Requires-Dist: black; extra == "dev"
Requires-Dist: flake8; extra == "dev"
Provides-Extra: jupyter
Requires-Dist: ipywidgets; extra == "jupyter"
Requires-Dist: jupyter; extra == "jupyter"
Dynamic: author
Dynamic: home-page
Dynamic: license-file
Dynamic: requires-python
